cognite/ingestion/__init__.py
cognite/ingestion/config.py
cognite/ingestion/data_types.py
cognite/ingestion/ingester.py
cognite/ingestion/queues.py
cognite/ingestion/retry.py
cognite_ingestion_library-0.1.0.dist-info/LICENSE
cognite_ingestion_library-0.1.0.dist-info/WHEEL
cognite_ingestion_library-0.1.0.dist-info/METADATA
cognite_ingestion_library-0.1.0.dist-info/RECORD
